streamlocal.py
streamlocal-0.0.0.dist-info/metadata.json
streamlocal-0.0.0.dist-info/RECORD
streamlocal-0.0.0.dist-info/METADATA
streamlocal-0.0.0.dist-info/DESCRIPTION.rst
streamlocal-0.0.0.dist-info/WHEEL
streamlocal-0.0.0.dist-info/top_level.txt
